pydfc/__init__.py
pydfc/data_loader.py
pydfc/dfc.py
pydfc/dfc_utils.py
pydfc/multi_analysis.py
pydfc/multi_analysis_utils.py
pydfc/task_utils.py
pydfc/time_series.py
pydfc/comparison/__init__.py
pydfc/comparison/analytical.py
pydfc/comparison/plotting.py
pydfc/comparison/similarity_assessment.py
pydfc/dfc_methods/__init__.py
pydfc/dfc_methods/base_dfc_method.py
pydfc/dfc_methods/cap.py
pydfc/dfc_methods/continuous_hmm.py
pydfc/dfc_methods/discrete_hmm.py
pydfc/dfc_methods/sliding_window.py
pydfc/dfc_methods/sliding_window_clustr.py
pydfc/dfc_methods/time_freq.py
pydfc/dfc_methods/windowless.py
pydfc-1.0.7.dist-info/METADATA
pydfc-1.0.7.dist-info/WHEEL
pydfc-1.0.7.dist-info/licenses/LICENSE
pydfc-1.0.7.dist-info/RECORD
