Metadata-Version: 2.4
Name: pydfc
Version: 1.0.7
Summary: This package aims to provide a comprehensive framework for assessing dynamic functional connectivity (dFC) using multiple methods and comparing results across methods.
Author: Mohammad Torabi
Maintainer-email: Mohammad Torabi <mohammad.torabi@mail.mcgill.ca>
License: MIT
License-File: LICENSE
Keywords: dFC package,neuroimaging,python
Classifier: Development Status :: 5 - Production/Stable
Classifier: Intended Audience :: Education
Classifier: Operating System :: MacOS :: MacOS X
Classifier: Operating System :: POSIX :: Linux
Classifier: Programming Language :: Python :: 3
Requires-Python: >=3.8
Requires-Dist: h5py
Requires-Dist: hmmlearn
Requires-Dist: ksvd
Requires-Dist: matplotlib
Requires-Dist: networkx
Requires-Dist: nilearn!=0.10.3,>=0.10.2
Requires-Dist: pycwt
Requires-Dist: seaborn
Requires-Dist: statsmodels
Provides-Extra: test
Requires-Dist: pytest; extra == 'test'
